ape/__init__.py
ape/__main__.py
ape/cli.py
ape/errors.py
ape/language_spec.py
ape/linker.py
ape/benchmarks/benchmark_runner.py
ape/codegen/__init__.py
ape/codegen/python_codegen.py
ape/compiler/__init__.py
ape/compiler/bytecode.py
ape/compiler/errors.py
ape/compiler/ir_nodes.py
ape/compiler/optimizer.py
ape/compiler/pipeline.py
ape/compiler/semantic_validator.py
ape/compiler/strictness_engine.py
ape/ir/__init__.py
ape/ir/ir_builder.py
ape/lang/__init__.py
ape/lang/base.py
ape/lang/de.py
ape/lang/en.py
ape/lang/es.py
ape/lang/fr.py
ape/lang/it.py
ape/lang/nl.py
ape/lang/pt.py
ape/lang/registry.py
ape/parser/__init__.py
ape/parser/ast_nodes.py
ape/parser/parser.py
ape/runtime/__init__.py
ape/runtime/constraint_checker.py
ape/runtime/context.py
ape/runtime/core.py
ape/runtime/decision_table.py
ape/runtime/errors.py
ape/runtime/executor.py
ape/runtime/explain.py
ape/runtime/policy_engine.py
ape/runtime/profile.py
ape/runtime/replay.py
ape/runtime/rule_engine.py
ape/runtime/trace.py
ape/std/__init__.py
ape/std/collections.py
ape/std/comparison.py
ape/std/datetime.py
ape/std/errors.py
ape/std/json.py
ape/std/logic.py
ape/std/math.py
ape/std/math_ext.py
ape/std/strings.py
ape/tokenizer/__init__.py
ape/tokenizer/tokenizer.py
ape/types/__init__.py
ape/types/datetime_type.py
ape/types/list_type.py
ape/types/map_type.py
ape/types/record_type.py
ape/types/tuple_type.py
ape/validator/types.py
ape/vm/__init__.py
ape/vm/instructions.py
ape/vm/vm.py
ape_lang-1.0.5.dist-info/licenses/LICENSE
ape_lang-1.0.5.dist-info/METADATA
ape_lang-1.0.5.dist-info/WHEEL
ape_lang-1.0.5.dist-info/entry_points.txt
ape_lang-1.0.5.dist-info/top_level.txt
ape_lang-1.0.5.dist-info/RECORD
