Metadata-Version: 2.4
Name: ape-lang
Version: 1.0.5
Summary: A deterministic AI-first programming language for unambiguous human-AI collaboration
Author-email: David Van Aelst <david@skyrah.be>
License: MIT
Keywords: programming-language,compiler,AI,deterministic,CDS,ape
Classifier: Programming Language :: Python :: 3.11
Classifier: License :: OSI Approved :: MIT License
Classifier: Development Status :: 3 - Alpha
Classifier: Environment :: Console
Classifier: Intended Audience :: Developers
Classifier: Topic :: Software Development :: Compilers
Classifier: Topic :: Software Development :: Code Generators
Requires-Python: >=3.11
License-File: LICENSE
Dynamic: license-file
